README.md
setup.py
kinesis/__init__.py
kinesis/base.py
kinesis/checkpointers.py
kinesis/consumer.py
kinesis/exceptions.py
kinesis/producer.py
py_kinesis.egg-info/PKG-INFO
py_kinesis.egg-info/SOURCES.txt
py_kinesis.egg-info/dependency_links.txt
py_kinesis.egg-info/requires.txt
py_kinesis.egg-info/top_level.txt