Metadata-Version: 2.1
Name: py-kinesis
Version: 0.0.1
Summary: AsyncIO Kinesis Library
Home-page: https://github.com/hampsterx/async-kinesis
Author: hampsterx
Author-email: tim.vdh@gmail.com
License: Apache2
Platform: UNKNOWN
Classifier: Development Status :: 4 - Beta
Classifier: Programming Language :: Python
Classifier: Programming Language :: Python :: 3
Classifier: Programming Language :: Python :: 3.5
Classifier: Programming Language :: Python :: 3.6
Classifier: Programming Language :: Python :: 3.7
Classifier: Intended Audience :: Developers
Classifier: License :: OSI Approved :: Apache Software License
Provides-Extra: redis
